tzx_easy_py/__init__.py
tzx_easy_py/test/__init__.py
tzx_easy_py_douly-0.0.1.dist-info/LICENSE
tzx_easy_py_douly-0.0.1.dist-info/METADATA
tzx_easy_py_douly-0.0.1.dist-info/WHEEL
tzx_easy_py_douly-0.0.1.dist-info/top_level.txt
tzx_easy_py_douly-0.0.1.dist-info/RECORD
