Metadata-Version: 2.1
Name: tzx-easy-py-douly
Version: 0.0.1
Summary: 天智祥信息科技有限公司python工具包
Home-page: https://fake.com/fake/fakeproject
Author: douly
Author-email: mitiandameng@gmail.com
License: UNKNOWN
Platform: UNKNOWN
Classifier: Programming Language :: Python :: 3
Classifier: License :: OSI Approved :: MIT License
Classifier: Operating System :: OS Independent
License-File: LICENSE
